{"cameraMode":{"drawMode":0,"name":"Shaded","section":"Shading Mode"},"sceneLighting":true,"audioPlay":false,"sceneViewState":{"m_AlwaysRefresh":false,"showFog":true,"showSkybox":true,"showFlares":true,"showImageEffects":true,"showParticleSystems":true,"showVisualEffectGraphs":true,"m_FxEnabled":true},"in2DMode":false,"pivot":{"x":27.81097412109375,"y":10.0,"z":-26.26129913330078},"rotation":{"x":0.1731978803873062,"y":-0.6156980395317078,"z":0.1411193311214447,"w":0.7556574940681458},"size":20.56146812438965,"orthographic":false}